Metadata-Version: 2.1
Name: Qter
Version: 0.2.3
Summary: A quantum simulator
Home-page: UNKNOWN
Author: Subhash Shankar Pandey
Author-email: subhashshankarpandeyy@gmail.com
License: UNKNOWN
Keywords: Quantum_simulator
Platform: UNKNOWN
Classifier: Development Status :: 5 - Production/Stable
Classifier: Intended Audience :: Education
Classifier: Operating System :: OS Independent
Classifier: License :: OSI Approved :: MIT License
Classifier: Programming Language :: Python :: 3
